src/example_package/__init__.py
src/example_package/pro1.py
multiplywith1000-0.0.1.dist-info/METADATA
multiplywith1000-0.0.1.dist-info/WHEEL
multiplywith1000-0.0.1.dist-info/licenses/LICENSE.txt
multiplywith1000-0.0.1.dist-info/RECORD
